{
  "users" : [ {
    "username" : "Alice",
    "access" : [ "print", "queue", "restart", "topQueue", "start", "stop", "restart", "status", "readConfig", "setConfig" ]
  }, {
    "username" : "Bob",
    "access" : [ "start", "stop", "restart", "status", "readConfig", "setConfig" ]
  }, {
    "username" : "Cecilie",
    "access" : [ "print", "queue", "restart", "topQueue" ]
  }, {
    "username" : "David",
    "access" : [ "print", "queue" ]
  }, {
    "username" : "Erica",
    "access" : [ "print", "queue" ]
  }, {
    "username" : "Fred",
    "access" : [ "print", "queue" ]
  }, {
    "username" : "George",
    "access" : [ "print", "queue" ]
  }
  ]
}